<?xml version="1.0" encoding="utf-8" ?>
<dwsync>
<file name="constrain-movement.html" server="frida2" local="130410179460000000" remote="130432684200000000" Dst="2" />
<file name="cursor-style.html" server="frida2" local="130410179460000000" remote="130432684200000000" Dst="2" />
<file name="default.html" server="frida2" local="130410179460000000" remote="130432684200000000" Dst="2" />
<file name="delay-start.html" server="frida2" local="130410179460000000" remote="130432684200000000" Dst="2" />
<file name="events.html" server="frida2" local="130410179460000000" remote="130432684200000000" Dst="2" />
<file name="handle.html" server="frida2" local="130410179460000000" remote="130432684200000000" Dst="2" />
<file name="index.html" server="frida2" local="130410179460000000" remote="130432684200000000" Dst="2" />
<file name="revert.html" server="frida2" local="130410179460000000" remote="130432684200000000" Dst="2" />
<file name="scroll.html" server="frida2" local="130410179460000000" remote="130432684200000000" Dst="2" />
<file name="snap-to.html" server="frida2" local="130410179460000000" remote="130432684200000000" Dst="2" />
<file name="sortable.html" server="frida2" local="130410179460000000" remote="130432684200000000" Dst="2" />
<file name="visual-feedback.html" server="frida2" local="130410179460000000" remote="130432684200000000" Dst="2" />
</dwsync>